MANIFEST.in
README.rst
bottle_elastic.py
requirements.txt
setup.py
bottle_elastic.egg-info/PKG-INFO
bottle_elastic.egg-info/SOURCES.txt
bottle_elastic.egg-info/dependency_links.txt
bottle_elastic.egg-info/requires.txt
bottle_elastic.egg-info/top_level.txt