Metadata-Version: 1.1
Name: bottle-elastic
Version: 0.2.1
Summary: Elasticsearch integration for Bottle
Home-page: https://github.com/bsao/bottle-elastic
Author: Robson Junior
Author-email: bsao@icloud.com
License: MIT
Platform: any
Classifier: Environment :: Web Environment
Classifier: Environment :: Plugins
Classifier: Framework :: Bottle
Classifier: Intended Audience :: Developers
Classifier: License :: OSI Approved :: MIT License
Classifier: Operating System :: OS Independent
Classifier: Programming Language :: Python
Classifier: Topic :: Internet :: WWW/HTTP :: Dynamic Content
Classifier: Topic :: Software Development :: Libraries :: Python Modules
